test/params.v
`define x 1

test/util.v
`include "params.v"

module util(
    clk,
    init,
    cnt,
);

input clk;
input init;
output reg [3:0] cnt;


always @(posedge clk or posedge init) begin
    if (init) cnt <= 0;
    else cnt += `x;
end


endmodule


module p(clk, in, out);

input           clk;
input   [3:0]   in;
output  [3:0]   out;

reg     [3:0]   x;
always@(posedge clk)
    x <= in;

assign out = x;

endmodule

test/test.v
`include "util.v"

// testbench
module test();

reg clk;
reg init;
wire [3:0] c;
wire [3:0] c1;
wire [3:0] c2;

// instantiate a dut (device under test)
util ut(
    .clk(clk),
    .init(init),
    .cnt(c)
);

// parameter ONE = 1;
// p p1(
//     .clk(clk),
//     .in(ONE),
//     .out(c1)
// );

// p p2(
//     .clk(clk),
//     .in(c1),
//     .out(c2)
// );



initial begin
    $dumpfile("test.vcd");
    $dumpvars(0, ut);

    clk = 0;
    init = 0;

    // initialize cnt in dut
    #1
    init = 1;
    #1

    init = 0;

    #100
    init=1;
    #1

    init=0;

end


always #10 begin
    clk = ~clk;

    // if (out == 4'b1111)
    //     $finish;
end


// in case bugs happen
always #400 begin
    $finish;
end


endmodule

test/test.vcd
$date
	Thu Dec  8 18:42:23 2022
$end
$version
	Icarus Verilog
$end
$timescale
	1s
$end
$scope module test $end
$scope module ut $end
$var wire 1 ! clk $end
$var wire 1 " init $end
$var reg 4 # cnt [3:0] $end
$upscope $end
$upscope $end
$enddefinitions $end
#0
$dumpvars
bx #
0"
0!
$end
#1
b0 #
1"
#2
0"
#10
b1 #
1!
#20
0!
#30
b10 #
1!
#40
0!
#50
b11 #
1!
#60
0!
#70
b100 #
1!
#80
0!
#90
b101 #
1!
#100
0!
#102
b0 #
1"
#103
0"
#110
b1 #
1!
#120
0!
#130
b10 #
1!
#140
0!
#150
b11 #
1!
#160
0!
#170
b100 #
1!
#180
0!
#190
b101 #
1!
#200
0!
#210
b110 #
1!
#220
0!
#230
b111 #
1!
#240
0!
#250
b1000 #
1!
#260
0!
#270
b1001 #
1!
#280
0!
#290
b1010 #
1!
#300
0!
#310
b1011 #
1!
#320
0!
#330
b1100 #
1!
#340
0!
#350
b1101 #
1!
#360
0!
#370
b1110 #
1!
#380
0!
#390
b1111 #
1!
